async2v/__init__.py
async2v/cli.py
async2v/error.py
async2v/event.py
async2v/fields.py
async2v/util.py
async2v/application/__init__.py
async2v/application/_graph.py
async2v/application/_registry.py
async2v/application/_runner.py
async2v/application/metric.py
async2v/components/__init__.py
async2v/components/base.py
async2v/components/opencv/__init__.py
async2v/components/opencv/projector.py
async2v/components/opencv/video.py
async2v/components/pygame/__init__.py
async2v/components/pygame/_layout.py
async2v/components/pygame/display.py
async2v/components/pygame/gui.py
async2v/components/pygame/keyboard.py
async2v/components/pygame/main.py
async2v/components/pygame/mouse.py
async2v/components/pygame/fonts/__init__.py
async2v/components/pygame/fonts/bedstead.otf
async2v-0.1.4.dist-info/LICENSE
async2v-0.1.4.dist-info/METADATA
async2v-0.1.4.dist-info/WHEEL
async2v-0.1.4.dist-info/top_level.txt
async2v-0.1.4.dist-info/RECORD
