Metadata-Version: 2.1
Name: async2v
Version: 0.1.4
Summary: Framework for building computer-vision prototypes
Home-page: UNKNOWN
Author: Thomas Reifenberger
License: MIT
Project-URL: Source on GitHub, https://github.com/tom-mi/python-async2v
Project-URL: Documentation, https://async2v.readthedocs.io/
Project-URL: Tests on Travis CI, https://travis-ci.com/tom-mi/python-async2v
Platform: UNKNOWN
Classifier: License :: OSI Approved :: MIT License
Classifier: Programming Language :: Python
Classifier: Programming Language :: Python :: 3.6
Classifier: Programming Language :: Python :: 3.7
Classifier: Development Status :: 4 - Beta
Classifier: Intended Audience :: Developers
Requires-Dist: argcomplete
Requires-Dist: graphviz
Requires-Dist: logwood
Requires-Dist: dataclasses ; python_version < "3.7"
Provides-Extra: opencv
Requires-Dist: opencv-python ; extra == 'opencv'
Requires-Dist: numpy ; extra == 'opencv'
Provides-Extra: pygame
Requires-Dist: pygame ; extra == 'pygame'
